{"stat.chestOpened":3,"stat.walkOneCm":36656,"stat.pickup.minecraft.bone":1,"stat.useItem.minecraft.sapling":1,"belph.learn":1,"stat.killEntity.primitivemobs.brain_slime":6,"stat.pickup.minecraft.nether_wart":3,"stat.damageTaken":1226,"stat.pickup.minecraft.feather":1,"stat.pickup.exoticbirds.booby_egg":1,"stat.mobKills":8,"stat.talkedToVillager":1,"stat.pickup.actuallyadditions.item_solidified_experience":1,"stat.useItem.minecraft.golden_apple":1,"stat.flyOneCm":8603,"stat.deaths":5,"belph.kill":1,"stat.entityKilledBy.wild_dog":1,"stat.jump":81,"stat.entityKilledBy.primitivemobs.brain_slime":1,"stat.swimOneCm":735,"stat.playOneMinute":14885,"stat.fallOneCm":2816,"stat.pickup.mysticalwildlife.plumper_meat_raw":2,"stat.sneakTime":25,"stat.pickup.minecraft.slime_ball":2,"stat.damageDealt":461,"stat.killEntity.rat":1,"stat.crouchOneCm":3,"stat.timeSinceDeath":0,"stat.pickup.lootbags.itemlootbag":1,"stat.sprintOneCm":25379,"stat.pickup.mysticalwildlife.plumper_blubber":2,"stat.diveOneCm":828}